__init__.py
Graph/__init__.py
Graph/button.py
Graph/frame.py
Graph/graph.py
Graph/label.py
Graph/window.py
Q_Learning/__init__.py
Q_Learning/q_learning_networkx.py
Q_Learning/q_learning_networkxv2.py
utils/__init__.py
utils/constants.py
Q_Learning_Graph_Visualization-0.1.0.dist-info/LICENSE
Q_Learning_Graph_Visualization-0.1.0.dist-info/METADATA
Q_Learning_Graph_Visualization-0.1.0.dist-info/WHEEL
Q_Learning_Graph_Visualization-0.1.0.dist-info/top_level.txt
Q_Learning_Graph_Visualization-0.1.0.dist-info/RECORD
