Metadata-Version: 2.2
Name: Q-Learning_Graph-Visualization
Version: 0.1.0
Summary: A Visualization regarding Q-Learning with a simple graph
Author-email: NTGNguyen <23521049@gm.uit.edu.vn>
License: MIT
Requires-Python: >=3.12
License-File: LICENSE
